ownerrezconnector/__init__.py
ownerrezconnector/api.py
ownerrezconnector/constants.py
ownerrezconnector/expeptions.py
ownerrezconnector/model.py
ownerrezconnector/restAdapter.py
ownerrezconnector/test/__init__.py
ownerrezconnector/test/context.py
ownerrezconnector/test/tests.py
ownerrezapi-0.0.4.dist-info/LICENSE
ownerrezapi-0.0.4.dist-info/METADATA
ownerrezapi-0.0.4.dist-info/WHEEL
ownerrezapi-0.0.4.dist-info/top_level.txt
ownerrezapi-0.0.4.dist-info/zip-safe
ownerrezapi-0.0.4.dist-info/RECORD
